LICENSE
README.rst
setup.py
starline/__init__.py
starline/auth_api.py
starline/base_api.py
starline/const.py
starline/device.py
starline/starline_api.py
starline.egg-info/PKG-INFO
starline.egg-info/SOURCES.txt
starline.egg-info/dependency_links.txt
starline.egg-info/requires.txt
starline.egg-info/top_level.txt